LICENSE
MANIFEST.in
README.md
README.rst
setup.cfg
setup.py
dftintegrate/__init__.py
dftintegrate/customserializer.py
dftintegrate/main.py
dftintegrate/msg.py
dftintegrate.egg-info/PKG-INFO
dftintegrate.egg-info/SOURCES.txt
dftintegrate.egg-info/dependency_links.txt
dftintegrate.egg-info/entry_points.txt
dftintegrate.egg-info/pbr.json
dftintegrate.egg-info/requires.txt
dftintegrate.egg-info/top_level.txt
dftintegrate/fourier/__init__.py
dftintegrate/fourier/converge.py
dftintegrate/fourier/evaluatefit.py
dftintegrate/fourier/fitdata.py
dftintegrate/fourier/integratedata.py
dftintegrate/fourier/readdata.py
dftintegrate/fourier/vaspdata.py