Metadata-Version: 1.1
Name: dftintegrate
Version: 0.1.2
Summary: Integrate DFT data
Home-page: https://github.com/mmb90/dftintegrate
Author: Matthew M Burbidge
Author-email: mmburbidge@gmail.com
License: MIT
Platform: UNKNOWN
Classifier: Development Status :: 4 - Beta
Classifier: Intended Audience :: Science/Research
Classifier: Natural Language :: English
Classifier: License :: OSI Approved :: MIT License
Classifier: Operating System :: MacOS
Classifier: Programming Language :: Python :: 3.4
Classifier: Topic :: Scientific/Engineering :: Information Analysis
